og_rabbit/__init__.py
og_rabbit/consumer.py
og_rabbit/publisher.py
og_rabbit-0.1.0.dist-info/METADATA
og_rabbit-0.1.0.dist-info/WHEEL
og_rabbit-0.1.0.dist-info/RECORD
