Metadata-Version: 2.1
Name: og-rabbit
Version: 0.1.0
Summary: 
Author: Nepich
Author-email: nepich@gmail.com
Requires-Python: >=3.11,<4.0
Classifier: Programming Language :: Python :: 3
Classifier: Programming Language :: Python :: 3.11
Requires-Dist: aio-pika (>=9.3.0,<10.0.0)
Requires-Dist: black (>=23.9.1,<24.0.0)
Requires-Dist: pika (>=1.3.2,<2.0.0)
Requires-Dist: ruff (>=0.0.292,<0.0.293)
